{
	"format_version": "1.8.0",
	"animations": {
		"animation.esfera": {
			"animation_length": 1.24,
			"bones": {
				"head": {
					"rotation": {
						"0.0": [2.5, 0, 0],
						"0.08": [2.5, 15, 0],
						"0.32": [2.5, 25, 0],
						"0.56": [-5, 5, -7.5]
					}
				},
				"body": {
					"rotation": {
						"0.0": [0, 7.5, 0],
						"0.32": [0, 15, 0]
					}
				},
				"rightLeg": {
					"rotation": {
						"0.16": [0, 7.5, 0],
						"0.4": [0, 12.5, 0]
					}
				},
				"leftLeg": {
					"rotation": {
						"0.08": [0, 10, 0],
						"0.32": [0, 20, 0]
					}
				},
				"leftArm": {
					"rotation": {
						"0.0": [0, 12.5, 0],
						"0.32": [0, 25, 0],
						"0.4": [0, 22.5, -7.5]
					}
				},
				"rightArm": {
					"rotation": {
						"0.16": [22.5, 0, 0],
						"0.4": [-15, 0, 0],
						"0.44": [-62.5, 0, 0],
						"0.48": [-102.5, 0, 0]
					}
				}
			}
		}
	}
}