{
	"format_version": "1.12.0",
	"minecraft:geometry": [
		{
			"description": {
				"identifier": "geometry.bloco_gunbai",
				"texture_width": 1300,
				"texture_height": 1300,
				"visible_bounds_width": 5,
				"visible_bounds_height": 3.5,
				"visible_bounds_offset": [0, 1.25, 0]
			},
			"bones": [
				{
					"name": "bloco_gunbai",
					"pivot": [-11.328, -18.688, 2.848],
					"rotation": [37.5, 0, 90]
				},
				{
					"name": "Gunbai",
					"parent": "bloco_gunbai",
					"pivot": [-24.96, -23.584, 26.784],
					"cubes": [
						{
							"origin": [-30.46, -19.934, -12.866],
							"size": [0, 21.5, 34.3],
							"uv": {
								"north": {"uv": [0, 0], "uv_size": [0, 18]},
								"east": {"uv": [0, 597], "uv_size": [25, 18]},
								"south": {"uv": [0, 0], "uv_size": [0, 18]},
								"west": {"uv": [81, 569], "uv_size": [1117, 690]},
								"up": {"uv": [0, 25], "uv_size": [0, -25]},
								"down": {"uv": [0, 25], "uv_size": [0, -25]}
							}
						},
						{
							"origin": [-31.06, -19.934, -12.866],
							"size": [0, 21.5, 34.3],
							"uv": {
								"north": {"uv": [0, 0], "uv_size": [0, 18]},
								"east": {"uv": [0, 597], "uv_size": [25, 18]},
								"south": {"uv": [0, 0], "uv_size": [0, 18]},
								"west": {"uv": [81, 569], "uv_size": [1117, 690]},
								"up": {"uv": [0, 25], "uv_size": [0, -25]},
								"down": {"uv": [0, 25], "uv_size": [0, -25]}
							}
						}
					]
				},
				{
					"name": "Cabo",
					"parent": "Gunbai",
					"pivot": [-30.96, -9.584, 4.784],
					"rotation": [0, 0, 90],
					"cubes": [
						{
							"origin": [-31.23051, -9.92605, -15.84463],
							"size": [0.13304, 0.13304, 17.3],
							"uv": {
								"north": {"uv": [50, 50], "uv_size": [0, 0]},
								"east": {"uv": [0, 50], "uv_size": [50, 0]},
								"south": {"uv": [100, 50], "uv_size": [0, 0]},
								"west": {"uv": [50, 50], "uv_size": [50, 0]},
								"up": {"uv": [50, 0], "uv_size": [0, 50]},
								"down": {"uv": [50, 50], "uv_size": [0, -50]}
							}
						},
						{
							"origin": [-31.23051, -9.04858, -15.84463],
							"size": [0.13304, 0.13304, 17.3],
							"uv": {
								"north": {"uv": [50, 50], "uv_size": [0, 0]},
								"east": {"uv": [0, 50], "uv_size": [50, 0]},
								"south": {"uv": [100, 50], "uv_size": [0, 0]},
								"west": {"uv": [50, 50], "uv_size": [50, 0]},
								"up": {"uv": [50, 0], "uv_size": [0, 50]},
								"down": {"uv": [50, 50], "uv_size": [0, -50]}
							}
						},
						{
							"origin": [-31.23051, -9.92605, -15.84463],
							"size": [0.13304, 0.13304, 17.3],
							"uv": {
								"north": {"uv": [50, 50], "uv_size": [0, 0]},
								"east": {"uv": [100, 50], "uv_size": [-50, 0]},
								"south": {"uv": [100, 50], "uv_size": [0, 0]},
								"west": {"uv": [50, 50], "uv_size": [-50, 0]},
								"up": {"uv": [50, 0], "uv_size": [0, 50]},
								"down": {"uv": [50, 50], "uv_size": [0, -50]}
							}
						},
						{
							"origin": [-31.23051, -9.04858, -15.84463],
							"size": [0.13304, 0.13304, 17.3],
							"uv": {
								"north": {"uv": [50, 50], "uv_size": [0, 0]},
								"east": {"uv": [100, 50], "uv_size": [-50, 0]},
								"south": {"uv": [100, 50], "uv_size": [0, 0]},
								"west": {"uv": [50, 50], "uv_size": [-50, 0]},
								"up": {"uv": [50, 0], "uv_size": [0, 50]},
								"down": {"uv": [50, 50], "uv_size": [0, -50]}
							}
						},
						{
							"origin": [-31.36355, -9.92605, -15.84463],
							"size": [0.13304, 0.13304, 17.3],
							"pivot": [-31.23051, -9.92605, 18.63283],
							"rotation": [0, 0, 15],
							"uv": {
								"north": {"uv": [50, 50], "uv_size": [0, 0]},
								"east": {"uv": [0, 50], "uv_size": [50, 0]},
								"south": {"uv": [100, 50], "uv_size": [0, 0]},
								"west": {"uv": [50, 50], "uv_size": [50, 0]},
								"up": {"uv": [50, 0], "uv_size": [0, 50]},
								"down": {"uv": [50, 50], "uv_size": [0, -50]}
							}
						},
						{
							"origin": [-31.36355, -9.04858, -15.84463],
							"size": [0.13304, 0.13304, 17.3],
							"pivot": [-31.23051, -8.91555, 18.63283],
							"rotation": [0, 0, -15],
							"uv": {
								"north": {"uv": [50, 50], "uv_size": [0, 0]},
								"east": {"uv": [0, 50], "uv_size": [50, 0]},
								"south": {"uv": [100, 50], "uv_size": [0, 0]},
								"west": {"uv": [50, 50], "uv_size": [50, 0]},
								"up": {"uv": [50, 0], "uv_size": [0, 50]},
								"down": {"uv": [50, 50], "uv_size": [0, -50]}
							}
						},
						{
							"origin": [-31.09749, -9.92605, -15.84463],
							"size": [0.13304, 0.13304, 17.3],
							"pivot": [-31.09749, -9.92605, 18.63283],
							"rotation": [0, 0, -15],
							"uv": {
								"north": {"uv": [50, 50], "uv_size": [0, 0]},
								"east": {"uv": [100, 50], "uv_size": [-50, 0]},
								"south": {"uv": [100, 50], "uv_size": [0, 0]},
								"west": {"uv": [50, 50], "uv_size": [-50, 0]},
								"up": {"uv": [50, 0], "uv_size": [0, 50]},
								"down": {"uv": [50, 50], "uv_size": [0, -50]}
							}
						},
						{
							"origin": [-31.09749, -9.04858, -15.84463],
							"size": [0.13304, 0.13304, 17.3],
							"pivot": [-31.09749, -8.91555, 18.63283],
							"rotation": [0, 0, 15],
							"uv": {
								"north": {"uv": [50, 50], "uv_size": [0, 0]},
								"east": {"uv": [100, 50], "uv_size": [-50, 0]},
								"south": {"uv": [100, 50], "uv_size": [0, 0]},
								"west": {"uv": [50, 50], "uv_size": [-50, 0]},
								"up": {"uv": [50, 0], "uv_size": [0, 50]},
								"down": {"uv": [50, 50], "uv_size": [0, -50]}
							}
						},
						{
							"origin": [-31.49205, -9.89161, -15.84463],
							"size": [0.13304, 0.13304, 17.3],
							"pivot": [-31.35901, -9.89161, 18.63283],
							"rotation": [0, 0, 30],
							"uv": {
								"north": {"uv": [50, 50], "uv_size": [0, 0]},
								"east": {"uv": [0, 50], "uv_size": [50, 0]},
								"south": {"uv": [100, 50], "uv_size": [0, 0]},
								"west": {"uv": [50, 50], "uv_size": [50, 0]},
								"up": {"uv": [50, 0], "uv_size": [0, 50]},
								"down": {"uv": [50, 50], "uv_size": [0, -50]}
							}
						},
						{
							"origin": [-31.49205, -9.08302, -15.84463],
							"size": [0.13304, 0.13304, 17.3],
							"pivot": [-31.35901, -8.94999, 18.63283],
							"rotation": [0, 0, -30],
							"uv": {
								"north": {"uv": [50, 50], "uv_size": [0, 0]},
								"east": {"uv": [0, 50], "uv_size": [50, 0]},
								"south": {"uv": [100, 50], "uv_size": [0, 0]},
								"west": {"uv": [50, 50], "uv_size": [50, 0]},
								"up": {"uv": [50, 0], "uv_size": [0, 50]},
								"down": {"uv": [50, 50], "uv_size": [0, -50]}
							}
						},
						{
							"origin": [-30.96899, -9.89161, -15.84463],
							"size": [0.13304, 0.13304, 17.3],
							"pivot": [-30.96899, -9.89161, 18.63283],
							"rotation": [0, 0, -30],
							"uv": {
								"north": {"uv": [50, 50], "uv_size": [0, 0]},
								"east": {"uv": [100, 50], "uv_size": [-50, 0]},
								"south": {"uv": [100, 50], "uv_size": [0, 0]},
								"west": {"uv": [50, 50], "uv_size": [-50, 0]},
								"up": {"uv": [50, 0], "uv_size": [0, 50]},
								"down": {"uv": [50, 50], "uv_size": [0, -50]}
							}
						},
						{
							"origin": [-30.96899, -9.08302, -15.84463],
							"size": [0.13304, 0.13304, 17.3],
							"pivot": [-30.96899, -8.94999, 18.63283],
							"rotation": [0, 0, 30],
							"uv": {
								"north": {"uv": [50, 50], "uv_size": [0, 0]},
								"east": {"uv": [100, 50], "uv_size": [-50, 0]},
								"south": {"uv": [100, 50], "uv_size": [0, 0]},
								"west": {"uv": [50, 50], "uv_size": [-50, 0]},
								"up": {"uv": [50, 0], "uv_size": [0, 50]},
								"down": {"uv": [50, 50], "uv_size": [0, -50]}
							}
						},
						{
							"origin": [-31.60727, -9.8251, -15.84463],
							"size": [0.13304, 0.13304, 17.3],
							"pivot": [-31.47423, -9.8251, 18.63283],
							"rotation": [0, 0, 45],
							"uv": {
								"north": {"uv": [50, 50], "uv_size": [0, 0]},
								"east": {"uv": [0, 50], "uv_size": [50, 0]},
								"south": {"uv": [100, 50], "uv_size": [0, 0]},
								"west": {"uv": [50, 50], "uv_size": [50, 0]},
								"up": {"uv": [50, 0], "uv_size": [0, 50]},
								"down": {"uv": [50, 50], "uv_size": [0, -50]}
							}
						},
						{
							"origin": [-31.60727, -9.14954, -15.84463],
							"size": [0.13304, 0.13304, 17.3],
							"pivot": [-31.47423, -9.0165, 18.63283],
							"rotation": [0, 0, -45],
							"uv": {
								"north": {"uv": [50, 50], "uv_size": [0, 0]},
								"east": {"uv": [0, 50], "uv_size": [50, 0]},
								"south": {"uv": [100, 50], "uv_size": [0, 0]},
								"west": {"uv": [50, 50], "uv_size": [50, 0]},
								"up": {"uv": [50, 0], "uv_size": [0, 50]},
								"down": {"uv": [50, 50], "uv_size": [0, -50]}
							}
						},
						{
							"origin": [-30.85377, -9.8251, -15.84463],
							"size": [0.13304, 0.13304, 17.3],
							"pivot": [-30.85377, -9.8251, 18.63283],
							"rotation": [0, 0, -45],
							"uv": {
								"north": {"uv": [50, 50], "uv_size": [0, 0]},
								"east": {"uv": [100, 50], "uv_size": [-50, 0]},
								"south": {"uv": [100, 50], "uv_size": [0, 0]},
								"west": {"uv": [50, 50], "uv_size": [-50, 0]},
								"up": {"uv": [50, 0], "uv_size": [0, 50]},
								"down": {"uv": [50, 50], "uv_size": [0, -50]}
							}
						},
						{
							"origin": [-30.85377, -9.14954, -15.84463],
							"size": [0.13304, 0.13304, 17.3],
							"pivot": [-30.85377, -9.0165, 18.63283],
							"rotation": [0, 0, 45],
							"uv": {
								"north": {"uv": [50, 50], "uv_size": [0, 0]},
								"east": {"uv": [100, 50], "uv_size": [-50, 0]},
								"south": {"uv": [100, 50], "uv_size": [0, 0]},
								"west": {"uv": [50, 50], "uv_size": [-50, 0]},
								"up": {"uv": [50, 0], "uv_size": [0, 50]},
								"down": {"uv": [50, 50], "uv_size": [0, -50]}
							}
						},
						{
							"origin": [-31.70134, -9.73103, -15.84463],
							"size": [0.13304, 0.13304, 17.3],
							"pivot": [-31.5683, -9.73103, 18.63283],
							"rotation": [0, 0, 60],
							"uv": {
								"north": {"uv": [50, 50], "uv_size": [0, 0]},
								"east": {"uv": [0, 50], "uv_size": [50, 0]},
								"south": {"uv": [100, 50], "uv_size": [0, 0]},
								"west": {"uv": [50, 50], "uv_size": [50, 0]},
								"up": {"uv": [50, 0], "uv_size": [0, 50]},
								"down": {"uv": [50, 50], "uv_size": [0, -50]}
							}
						},
						{
							"origin": [-31.70134, -9.2436, -15.84463],
							"size": [0.13304, 0.13304, 17.3],
							"pivot": [-31.5683, -9.11057, 18.63283],
							"rotation": [0, 0, -60],
							"uv": {
								"north": {"uv": [50, 50], "uv_size": [0, 0]},
								"east": {"uv": [0, 50], "uv_size": [50, 0]},
								"south": {"uv": [100, 50], "uv_size": [0, 0]},
								"west": {"uv": [50, 50], "uv_size": [50, 0]},
								"up": {"uv": [50, 0], "uv_size": [0, 50]},
								"down": {"uv": [50, 50], "uv_size": [0, -50]}
							}
						},
						{
							"origin": [-30.7597, -9.73103, -15.84463],
							"size": [0.13304, 0.13304, 17.3],
							"pivot": [-30.7597, -9.73103, 18.63283],
							"rotation": [0, 0, -60],
							"uv": {
								"north": {"uv": [50, 50], "uv_size": [0, 0]},
								"east": {"uv": [100, 50], "uv_size": [-50, 0]},
								"south": {"uv": [100, 50], "uv_size": [0, 0]},
								"west": {"uv": [50, 50], "uv_size": [-50, 0]},
								"up": {"uv": [50, 0], "uv_size": [0, 50]},
								"down": {"uv": [50, 50], "uv_size": [0, -50]}
							}
						},
						{
							"origin": [-30.7597, -9.2436, -15.84463],
							"size": [0.13304, 0.13304, 17.3],
							"pivot": [-30.7597, -9.11057, 18.63283],
							"rotation": [0, 0, 60],
							"uv": {
								"north": {"uv": [50, 50], "uv_size": [0, 0]},
								"east": {"uv": [100, 50], "uv_size": [-50, 0]},
								"south": {"uv": [100, 50], "uv_size": [0, 0]},
								"west": {"uv": [50, 50], "uv_size": [-50, 0]},
								"up": {"uv": [50, 0], "uv_size": [0, 50]},
								"down": {"uv": [50, 50], "uv_size": [0, -50]}
							}
						},
						{
							"origin": [-31.76785, -9.61581, -15.84463],
							"size": [0.13304, 0.13304, 17.3],
							"pivot": [-31.63481, -9.61581, 18.63283],
							"rotation": [0, 0, 75],
							"uv": {
								"north": {"uv": [50, 50], "uv_size": [0, 0]},
								"east": {"uv": [0, 50], "uv_size": [50, 0]},
								"south": {"uv": [100, 50], "uv_size": [0, 0]},
								"west": {"uv": [50, 50], "uv_size": [50, 0]},
								"up": {"uv": [50, 0], "uv_size": [0, 50]},
								"down": {"uv": [50, 50], "uv_size": [0, -50]}
							}
						},
						{
							"origin": [-31.76785, -9.35882, -15.84463],
							"size": [0.13304, 0.13304, 17.3],
							"pivot": [-31.63481, -9.22579, 18.63283],
							"rotation": [0, 0, -75],
							"uv": {
								"north": {"uv": [50, 50], "uv_size": [0, 0]},
								"east": {"uv": [0, 50], "uv_size": [50, 0]},
								"south": {"uv": [100, 50], "uv_size": [0, 0]},
								"west": {"uv": [50, 50], "uv_size": [50, 0]},
								"up": {"uv": [50, 0], "uv_size": [0, 50]},
								"down": {"uv": [50, 50], "uv_size": [0, -50]}
							}
						},
						{
							"origin": [-30.69319, -9.61581, -15.84463],
							"size": [0.13304, 0.13304, 17.3],
							"pivot": [-30.69319, -9.61581, 18.63283],
							"rotation": [0, 0, -75],
							"uv": {
								"north": {"uv": [50, 50], "uv_size": [0, 0]},
								"east": {"uv": [100, 50], "uv_size": [-50, 0]},
								"south": {"uv": [100, 50], "uv_size": [0, 0]},
								"west": {"uv": [50, 50], "uv_size": [-50, 0]},
								"up": {"uv": [50, 0], "uv_size": [0, 50]},
								"down": {"uv": [50, 50], "uv_size": [0, -50]}
							}
						},
						{
							"origin": [-30.69319, -9.35882, -15.84463],
							"size": [0.13304, 0.13304, 17.3],
							"pivot": [-30.69319, -9.22579, 18.63283],
							"rotation": [0, 0, 75],
							"uv": {
								"north": {"uv": [50, 50], "uv_size": [0, 0]},
								"east": {"uv": [100, 50], "uv_size": [-50, 0]},
								"south": {"uv": [100, 50], "uv_size": [0, 0]},
								"west": {"uv": [50, 50], "uv_size": [-50, 0]},
								"up": {"uv": [50, 0], "uv_size": [0, 50]},
								"down": {"uv": [50, 50], "uv_size": [0, -50]}
							}
						},
						{
							"origin": [-31.80229, -9.48731, -15.84463],
							"size": [0.13304, 0.13304, 17.3],
							"pivot": [-31.66925, -9.48731, 18.63283],
							"rotation": [0, 0, 90],
							"uv": {
								"north": {"uv": [50, 50], "uv_size": [0, 0]},
								"east": {"uv": [0, 50], "uv_size": [50, 0]},
								"south": {"uv": [100, 50], "uv_size": [0, 0]},
								"west": {"uv": [50, 50], "uv_size": [50, 0]},
								"up": {"uv": [50, 0], "uv_size": [0, 50]},
								"down": {"uv": [50, 50], "uv_size": [0, -50]}
							}
						},
						{
							"origin": [-31.80229, -9.48731, -15.84463],
							"size": [0.13304, 0.13304, 17.3],
							"pivot": [-31.66925, -9.35429, 18.63283],
							"rotation": [0, 0, -90],
							"uv": {
								"north": {"uv": [50, 50], "uv_size": [0, 0]},
								"east": {"uv": [0, 50], "uv_size": [50, 0]},
								"south": {"uv": [100, 50], "uv_size": [0, 0]},
								"west": {"uv": [50, 50], "uv_size": [50, 0]},
								"up": {"uv": [50, 0], "uv_size": [0, 50]},
								"down": {"uv": [50, 50], "uv_size": [0, -50]}
							}
						},
						{
							"origin": [-30.65875, -9.48731, -15.84463],
							"size": [0.13304, 0.13304, 17.3],
							"pivot": [-30.65875, -9.48731, 18.63283],
							"rotation": [0, 0, -90],
							"uv": {
								"north": {"uv": [50, 50], "uv_size": [0, 0]},
								"east": {"uv": [100, 50], "uv_size": [-50, 0]},
								"south": {"uv": [100, 50], "uv_size": [0, 0]},
								"west": {"uv": [50, 50], "uv_size": [-50, 0]},
								"up": {"uv": [50, 0], "uv_size": [0, 50]},
								"down": {"uv": [50, 50], "uv_size": [0, -50]}
							}
						},
						{
							"origin": [-30.65875, -9.48731, -15.84463],
							"size": [0.13304, 0.13304, 17.3],
							"pivot": [-30.65875, -9.35429, 18.63283],
							"rotation": [0, 0, 90],
							"uv": {
								"north": {"uv": [50, 50], "uv_size": [0, 0]},
								"east": {"uv": [100, 50], "uv_size": [-50, 0]},
								"south": {"uv": [100, 50], "uv_size": [0, 0]},
								"west": {"uv": [50, 50], "uv_size": [-50, 0]},
								"up": {"uv": [50, 0], "uv_size": [0, 50]},
								"down": {"uv": [50, 50], "uv_size": [0, -50]}
							}
						}
					]
				},
				{
					"name": "Cabo2",
					"parent": "Gunbai",
					"pivot": [-30.96, -9.584, 4.784],
					"rotation": [0, 0, 90],
					"cubes": [
						{
							"origin": [-31.23051, -9.92605, 10.184],
							"size": [0.13304, 0.13304, 24.3],
							"uv": {
								"north": {"uv": [50, 50], "uv_size": [0, 0]},
								"east": {"uv": [0, 50], "uv_size": [50, 0]},
								"south": {"uv": [100, 50], "uv_size": [0, 0]},
								"west": {"uv": [50, 50], "uv_size": [50, 0]},
								"up": {"uv": [50, 0], "uv_size": [0, 50]},
								"down": {"uv": [50, 50], "uv_size": [0, -50]}
							}
						},
						{
							"origin": [-31.23051, -9.04858, 10.184],
							"size": [0.13304, 0.13304, 24.3],
							"uv": {
								"north": {"uv": [50, 50], "uv_size": [0, 0]},
								"east": {"uv": [0, 50], "uv_size": [50, 0]},
								"south": {"uv": [100, 50], "uv_size": [0, 0]},
								"west": {"uv": [50, 50], "uv_size": [50, 0]},
								"up": {"uv": [50, 0], "uv_size": [0, 50]},
								"down": {"uv": [50, 50], "uv_size": [0, -50]}
							}
						},
						{
							"origin": [-31.23051, -9.92605, 10.184],
							"size": [0.13304, 0.13304, 24.3],
							"uv": {
								"north": {"uv": [50, 50], "uv_size": [0, 0]},
								"east": {"uv": [100, 50], "uv_size": [-50, 0]},
								"south": {"uv": [100, 50], "uv_size": [0, 0]},
								"west": {"uv": [50, 50], "uv_size": [-50, 0]},
								"up": {"uv": [50, 0], "uv_size": [0, 50]},
								"down": {"uv": [50, 50], "uv_size": [0, -50]}
							}
						},
						{
							"origin": [-31.23051, -9.04858, 10.184],
							"size": [0.13304, 0.13304, 24.3],
							"uv": {
								"north": {"uv": [50, 50], "uv_size": [0, 0]},
								"east": {"uv": [100, 50], "uv_size": [-50, 0]},
								"south": {"uv": [100, 50], "uv_size": [0, 0]},
								"west": {"uv": [50, 50], "uv_size": [-50, 0]},
								"up": {"uv": [50, 0], "uv_size": [0, 50]},
								"down": {"uv": [50, 50], "uv_size": [0, -50]}
							}
						},
						{
							"origin": [-31.36355, -9.92605, 10.184],
							"size": [0.13304, 0.13304, 24.3],
							"pivot": [-31.23051, -9.92605, 18.63283],
							"rotation": [0, 0, 15],
							"uv": {
								"north": {"uv": [50, 50], "uv_size": [0, 0]},
								"east": {"uv": [0, 50], "uv_size": [50, 0]},
								"south": {"uv": [100, 50], "uv_size": [0, 0]},
								"west": {"uv": [50, 50], "uv_size": [50, 0]},
								"up": {"uv": [50, 0], "uv_size": [0, 50]},
								"down": {"uv": [50, 50], "uv_size": [0, -50]}
							}
						},
						{
							"origin": [-31.36355, -9.04858, 10.184],
							"size": [0.13304, 0.13304, 24.3],
							"pivot": [-31.23051, -8.91555, 18.63283],
							"rotation": [0, 0, -15],
							"uv": {
								"north": {"uv": [50, 50], "uv_size": [0, 0]},
								"east": {"uv": [0, 50], "uv_size": [50, 0]},
								"south": {"uv": [100, 50], "uv_size": [0, 0]},
								"west": {"uv": [50, 50], "uv_size": [50, 0]},
								"up": {"uv": [50, 0], "uv_size": [0, 50]},
								"down": {"uv": [50, 50], "uv_size": [0, -50]}
							}
						},
						{
							"origin": [-31.09749, -9.92605, 10.184],
							"size": [0.13304, 0.13304, 24.3],
							"pivot": [-31.09749, -9.92605, 18.63283],
							"rotation": [0, 0, -15],
							"uv": {
								"north": {"uv": [50, 50], "uv_size": [0, 0]},
								"east": {"uv": [100, 50], "uv_size": [-50, 0]},
								"south": {"uv": [100, 50], "uv_size": [0, 0]},
								"west": {"uv": [50, 50], "uv_size": [-50, 0]},
								"up": {"uv": [50, 0], "uv_size": [0, 50]},
								"down": {"uv": [50, 50], "uv_size": [0, -50]}
							}
						},
						{
							"origin": [-31.09749, -9.04858, 10.184],
							"size": [0.13304, 0.13304, 24.3],
							"pivot": [-31.09749, -8.91555, 18.63283],
							"rotation": [0, 0, 15],
							"uv": {
								"north": {"uv": [50, 50], "uv_size": [0, 0]},
								"east": {"uv": [100, 50], "uv_size": [-50, 0]},
								"south": {"uv": [100, 50], "uv_size": [0, 0]},
								"west": {"uv": [50, 50], "uv_size": [-50, 0]},
								"up": {"uv": [50, 0], "uv_size": [0, 50]},
								"down": {"uv": [50, 50], "uv_size": [0, -50]}
							}
						},
						{
							"origin": [-31.49205, -9.89161, 10.184],
							"size": [0.13304, 0.13304, 24.3],
							"pivot": [-31.35901, -9.89161, 18.63283],
							"rotation": [0, 0, 30],
							"uv": {
								"north": {"uv": [50, 50], "uv_size": [0, 0]},
								"east": {"uv": [0, 50], "uv_size": [50, 0]},
								"south": {"uv": [100, 50], "uv_size": [0, 0]},
								"west": {"uv": [50, 50], "uv_size": [50, 0]},
								"up": {"uv": [50, 0], "uv_size": [0, 50]},
								"down": {"uv": [50, 50], "uv_size": [0, -50]}
							}
						},
						{
							"origin": [-31.49205, -9.08302, 10.184],
							"size": [0.13304, 0.13304, 24.3],
							"pivot": [-31.35901, -8.94999, 18.63283],
							"rotation": [0, 0, -30],
							"uv": {
								"north": {"uv": [50, 50], "uv_size": [0, 0]},
								"east": {"uv": [0, 50], "uv_size": [50, 0]},
								"south": {"uv": [100, 50], "uv_size": [0, 0]},
								"west": {"uv": [50, 50], "uv_size": [50, 0]},
								"up": {"uv": [50, 0], "uv_size": [0, 50]},
								"down": {"uv": [50, 50], "uv_size": [0, -50]}
							}
						},
						{
							"origin": [-30.96899, -9.89161, 10.184],
							"size": [0.13304, 0.13304, 24.3],
							"pivot": [-30.96899, -9.89161, 18.63283],
							"rotation": [0, 0, -30],
							"uv": {
								"north": {"uv": [50, 50], "uv_size": [0, 0]},
								"east": {"uv": [100, 50], "uv_size": [-50, 0]},
								"south": {"uv": [100, 50], "uv_size": [0, 0]},
								"west": {"uv": [50, 50], "uv_size": [-50, 0]},
								"up": {"uv": [50, 0], "uv_size": [0, 50]},
								"down": {"uv": [50, 50], "uv_size": [0, -50]}
							}
						},
						{
							"origin": [-30.96899, -9.08302, 10.184],
							"size": [0.13304, 0.13304, 24.3],
							"pivot": [-30.96899, -8.94999, 18.63283],
							"rotation": [0, 0, 30],
							"uv": {
								"north": {"uv": [50, 50], "uv_size": [0, 0]},
								"east": {"uv": [100, 50], "uv_size": [-50, 0]},
								"south": {"uv": [100, 50], "uv_size": [0, 0]},
								"west": {"uv": [50, 50], "uv_size": [-50, 0]},
								"up": {"uv": [50, 0], "uv_size": [0, 50]},
								"down": {"uv": [50, 50], "uv_size": [0, -50]}
							}
						},
						{
							"origin": [-31.60727, -9.8251, 10.184],
							"size": [0.13304, 0.13304, 24.3],
							"pivot": [-31.47423, -9.8251, 18.63283],
							"rotation": [0, 0, 45],
							"uv": {
								"north": {"uv": [50, 50], "uv_size": [0, 0]},
								"east": {"uv": [0, 50], "uv_size": [50, 0]},
								"south": {"uv": [100, 50], "uv_size": [0, 0]},
								"west": {"uv": [50, 50], "uv_size": [50, 0]},
								"up": {"uv": [50, 0], "uv_size": [0, 50]},
								"down": {"uv": [50, 50], "uv_size": [0, -50]}
							}
						},
						{
							"origin": [-31.60727, -9.14954, 10.184],
							"size": [0.13304, 0.13304, 24.3],
							"pivot": [-31.47423, -9.0165, 18.63283],
							"rotation": [0, 0, -45],
							"uv": {
								"north": {"uv": [50, 50], "uv_size": [0, 0]},
								"east": {"uv": [0, 50], "uv_size": [50, 0]},
								"south": {"uv": [100, 50], "uv_size": [0, 0]},
								"west": {"uv": [50, 50], "uv_size": [50, 0]},
								"up": {"uv": [50, 0], "uv_size": [0, 50]},
								"down": {"uv": [50, 50], "uv_size": [0, -50]}
							}
						},
						{
							"origin": [-30.85377, -9.8251, 10.184],
							"size": [0.13304, 0.13304, 24.3],
							"pivot": [-30.85377, -9.8251, 18.63283],
							"rotation": [0, 0, -45],
							"uv": {
								"north": {"uv": [50, 50], "uv_size": [0, 0]},
								"east": {"uv": [100, 50], "uv_size": [-50, 0]},
								"south": {"uv": [100, 50], "uv_size": [0, 0]},
								"west": {"uv": [50, 50], "uv_size": [-50, 0]},
								"up": {"uv": [50, 0], "uv_size": [0, 50]},
								"down": {"uv": [50, 50], "uv_size": [0, -50]}
							}
						},
						{
							"origin": [-30.85377, -9.14954, 10.184],
							"size": [0.13304, 0.13304, 24.3],
							"pivot": [-30.85377, -9.0165, 18.63283],
							"rotation": [0, 0, 45],
							"uv": {
								"north": {"uv": [50, 50], "uv_size": [0, 0]},
								"east": {"uv": [100, 50], "uv_size": [-50, 0]},
								"south": {"uv": [100, 50], "uv_size": [0, 0]},
								"west": {"uv": [50, 50], "uv_size": [-50, 0]},
								"up": {"uv": [50, 0], "uv_size": [0, 50]},
								"down": {"uv": [50, 50], "uv_size": [0, -50]}
							}
						},
						{
							"origin": [-31.70134, -9.73103, 10.184],
							"size": [0.13304, 0.13304, 24.3],
							"pivot": [-31.5683, -9.73103, 18.63283],
							"rotation": [0, 0, 60],
							"uv": {
								"north": {"uv": [50, 50], "uv_size": [0, 0]},
								"east": {"uv": [0, 50], "uv_size": [50, 0]},
								"south": {"uv": [100, 50], "uv_size": [0, 0]},
								"west": {"uv": [50, 50], "uv_size": [50, 0]},
								"up": {"uv": [50, 0], "uv_size": [0, 50]},
								"down": {"uv": [50, 50], "uv_size": [0, -50]}
							}
						},
						{
							"origin": [-31.70134, -9.2436, 10.184],
							"size": [0.13304, 0.13304, 24.3],
							"pivot": [-31.5683, -9.11057, 18.63283],
							"rotation": [0, 0, -60],
							"uv": {
								"north": {"uv": [50, 50], "uv_size": [0, 0]},
								"east": {"uv": [0, 50], "uv_size": [50, 0]},
								"south": {"uv": [100, 50], "uv_size": [0, 0]},
								"west": {"uv": [50, 50], "uv_size": [50, 0]},
								"up": {"uv": [50, 0], "uv_size": [0, 50]},
								"down": {"uv": [50, 50], "uv_size": [0, -50]}
							}
						},
						{
							"origin": [-30.7597, -9.73103, 10.184],
							"size": [0.13304, 0.13304, 24.3],
							"pivot": [-30.7597, -9.73103, 18.63283],
							"rotation": [0, 0, -60],
							"uv": {
								"north": {"uv": [50, 50], "uv_size": [0, 0]},
								"east": {"uv": [100, 50], "uv_size": [-50, 0]},
								"south": {"uv": [100, 50], "uv_size": [0, 0]},
								"west": {"uv": [50, 50], "uv_size": [-50, 0]},
								"up": {"uv": [50, 0], "uv_size": [0, 50]},
								"down": {"uv": [50, 50], "uv_size": [0, -50]}
							}
						},
						{
							"origin": [-30.7597, -9.2436, 10.184],
							"size": [0.13304, 0.13304, 24.3],
							"pivot": [-30.7597, -9.11057, 18.63283],
							"rotation": [0, 0, 60],
							"uv": {
								"north": {"uv": [50, 50], "uv_size": [0, 0]},
								"east": {"uv": [100, 50], "uv_size": [-50, 0]},
								"south": {"uv": [100, 50], "uv_size": [0, 0]},
								"west": {"uv": [50, 50], "uv_size": [-50, 0]},
								"up": {"uv": [50, 0], "uv_size": [0, 50]},
								"down": {"uv": [50, 50], "uv_size": [0, -50]}
							}
						},
						{
							"origin": [-31.76785, -9.61581, 10.184],
							"size": [0.13304, 0.13304, 24.3],
							"pivot": [-31.63481, -9.61581, 18.63283],
							"rotation": [0, 0, 75],
							"uv": {
								"north": {"uv": [50, 50], "uv_size": [0, 0]},
								"east": {"uv": [0, 50], "uv_size": [50, 0]},
								"south": {"uv": [100, 50], "uv_size": [0, 0]},
								"west": {"uv": [50, 50], "uv_size": [50, 0]},
								"up": {"uv": [50, 0], "uv_size": [0, 50]},
								"down": {"uv": [50, 50], "uv_size": [0, -50]}
							}
						},
						{
							"origin": [-31.76785, -9.35882, 10.184],
							"size": [0.13304, 0.13304, 24.3],
							"pivot": [-31.63481, -9.22579, 18.63283],
							"rotation": [0, 0, -75],
							"uv": {
								"north": {"uv": [50, 50], "uv_size": [0, 0]},
								"east": {"uv": [0, 50], "uv_size": [50, 0]},
								"south": {"uv": [100, 50], "uv_size": [0, 0]},
								"west": {"uv": [50, 50], "uv_size": [50, 0]},
								"up": {"uv": [50, 0], "uv_size": [0, 50]},
								"down": {"uv": [50, 50], "uv_size": [0, -50]}
							}
						},
						{
							"origin": [-30.69319, -9.61581, 10.184],
							"size": [0.13304, 0.13304, 24.3],
							"pivot": [-30.69319, -9.61581, 18.63283],
							"rotation": [0, 0, -75],
							"uv": {
								"north": {"uv": [50, 50], "uv_size": [0, 0]},
								"east": {"uv": [100, 50], "uv_size": [-50, 0]},
								"south": {"uv": [100, 50], "uv_size": [0, 0]},
								"west": {"uv": [50, 50], "uv_size": [-50, 0]},
								"up": {"uv": [50, 0], "uv_size": [0, 50]},
								"down": {"uv": [50, 50], "uv_size": [0, -50]}
							}
						},
						{
							"origin": [-30.69319, -9.35882, 10.184],
							"size": [0.13304, 0.13304, 24.3],
							"pivot": [-30.69319, -9.22579, 18.63283],
							"rotation": [0, 0, 75],
							"uv": {
								"north": {"uv": [50, 50], "uv_size": [0, 0]},
								"east": {"uv": [100, 50], "uv_size": [-50, 0]},
								"south": {"uv": [100, 50], "uv_size": [0, 0]},
								"west": {"uv": [50, 50], "uv_size": [-50, 0]},
								"up": {"uv": [50, 0], "uv_size": [0, 50]},
								"down": {"uv": [50, 50], "uv_size": [0, -50]}
							}
						},
						{
							"origin": [-31.80229, -9.48731, 10.184],
							"size": [0.13304, 0.13304, 24.3],
							"pivot": [-31.66925, -9.48731, 18.63283],
							"rotation": [0, 0, 90],
							"uv": {
								"north": {"uv": [50, 50], "uv_size": [0, 0]},
								"east": {"uv": [0, 50], "uv_size": [50, 0]},
								"south": {"uv": [100, 50], "uv_size": [0, 0]},
								"west": {"uv": [50, 50], "uv_size": [50, 0]},
								"up": {"uv": [50, 0], "uv_size": [0, 50]},
								"down": {"uv": [50, 50], "uv_size": [0, -50]}
							}
						},
						{
							"origin": [-31.80229, -9.48731, 10.184],
							"size": [0.13304, 0.13304, 24.3],
							"pivot": [-31.66925, -9.35429, 18.63283],
							"rotation": [0, 0, -90],
							"uv": {
								"north": {"uv": [50, 50], "uv_size": [0, 0]},
								"east": {"uv": [0, 50], "uv_size": [50, 0]},
								"south": {"uv": [100, 50], "uv_size": [0, 0]},
								"west": {"uv": [50, 50], "uv_size": [50, 0]},
								"up": {"uv": [50, 0], "uv_size": [0, 50]},
								"down": {"uv": [50, 50], "uv_size": [0, -50]}
							}
						},
						{
							"origin": [-30.65875, -9.48731, 10.184],
							"size": [0.13304, 0.13304, 24.3],
							"pivot": [-30.65875, -9.48731, 18.63283],
							"rotation": [0, 0, -90],
							"uv": {
								"north": {"uv": [50, 50], "uv_size": [0, 0]},
								"east": {"uv": [100, 50], "uv_size": [-50, 0]},
								"south": {"uv": [100, 50], "uv_size": [0, 0]},
								"west": {"uv": [50, 50], "uv_size": [-50, 0]},
								"up": {"uv": [50, 0], "uv_size": [0, 50]},
								"down": {"uv": [50, 50], "uv_size": [0, -50]}
							}
						},
						{
							"origin": [-30.65875, -9.48731, 10.184],
							"size": [0.13304, 0.13304, 24.3],
							"pivot": [-30.65875, -9.35429, 18.63283],
							"rotation": [0, 0, 90],
							"uv": {
								"north": {"uv": [50, 50], "uv_size": [0, 0]},
								"east": {"uv": [100, 50], "uv_size": [-50, 0]},
								"south": {"uv": [100, 50], "uv_size": [0, 0]},
								"west": {"uv": [50, 50], "uv_size": [-50, 0]},
								"up": {"uv": [50, 0], "uv_size": [0, 50]},
								"down": {"uv": [50, 50], "uv_size": [0, -50]}
							}
						}
					]
				},
				{
					"name": "Circulos",
					"parent": "Gunbai",
					"pivot": [-42.76, 8.416, 42.984],
					"rotation": [0, 0, 90],
					"cubes": [
						{
							"origin": [-26.048, 20.128, 12.824],
							"size": [2.176, 0.576, 8.576],
							"uv": {
								"north": {"uv": [1034.24479, 169.27083], "uv_size": [1.69271, 0]},
								"east": {"uv": [988.54167, 223.4375], "uv_size": [8.46354, 0]},
								"south": {"uv": [1078.25521, 155.72917], "uv_size": [1.69271, 0]},
								"west": {"uv": [1186.58854, 179.42708], "uv_size": [8.46354, 0]},
								"up": {"uv": [1098.56771, 187.89062], "uv_size": [1.69271, 8.46354]},
								"down": {"uv": [1073.17708, 274.21875], "uv_size": [1.69271, -8.46354]}
							}
						},
						{
							"origin": [-26.048, 20.128, -11.12836],
							"size": [2.176, 0.576, 22.976],
							"uv": {
								"north": {"uv": [1034.24479, 169.27083], "uv_size": [1.69271, 0]},
								"east": {"uv": [988.54167, 223.4375], "uv_size": [8.46354, 0]},
								"south": {"uv": [1078.25521, 155.72917], "uv_size": [1.69271, 0]},
								"west": {"uv": [1186.58854, 179.42708], "uv_size": [8.46354, 0]},
								"up": {"uv": [1098.56771, 187.89062], "uv_size": [1.69271, 8.46354]},
								"down": {"uv": [1073.17708, 274.21875], "uv_size": [1.69271, -8.46354]}
							}
						},
						{
							"origin": [-26.048, 20.128, 19.224],
							"size": [2.176, 0.576, 2.176],
							"uv": {
								"north": {"uv": [1034.24479, 169.27083], "uv_size": [1.69271, 0]},
								"east": {"uv": [988.54167, 223.4375], "uv_size": [8.46354, 0]},
								"south": {"uv": [1078.25521, 155.72917], "uv_size": [1.69271, 0]},
								"west": {"uv": [1186.58854, 179.42708], "uv_size": [8.46354, 0]},
								"up": {"uv": [1098.56771, 187.89062], "uv_size": [1.69271, 8.46354]},
								"down": {"uv": [1073.17708, 274.21875], "uv_size": [1.69271, -8.46354]}
							}
						},
						{
							"origin": [-26.048, 20.128, 4.87164],
							"size": [2.176, 0.576, 2.176],
							"uv": {
								"north": {"uv": [1034.24479, 169.27083], "uv_size": [1.69271, 0]},
								"east": {"uv": [988.54167, 223.4375], "uv_size": [8.46354, 0]},
								"south": {"uv": [1078.25521, 155.72917], "uv_size": [1.69271, 0]},
								"west": {"uv": [1186.58854, 179.42708], "uv_size": [8.46354, 0]},
								"up": {"uv": [1098.56771, 187.89062], "uv_size": [1.69271, 8.46354]},
								"down": {"uv": [1073.17708, 274.21875], "uv_size": [1.69271, -8.46354]}
							}
						},
						{
							"origin": [-29.23785, 20.128, 12.55234],
							"size": [2.176, 0.576, 8.576],
							"pivot": [-27.06185, 20.128, 18.95234],
							"rotation": [0, -30, 0],
							"uv": {
								"north": {"uv": [1034.24479, 169.27083], "uv_size": [1.69271, 0]},
								"east": {"uv": [988.54167, 223.4375], "uv_size": [8.46354, 0]},
								"south": {"uv": [1078.25521, 155.72917], "uv_size": [1.69271, 0]},
								"west": {"uv": [1186.58854, 179.42708], "uv_size": [8.46354, 0]},
								"up": {"uv": [1098.56771, 187.89062], "uv_size": [1.69271, 8.46354]},
								"down": {"uv": [1073.17708, 274.21875], "uv_size": [1.69271, -8.46354]}
							}
						},
						{
							"origin": [-29.23785, 20.128, 5.1433],
							"size": [2.176, 0.576, 7.776],
							"pivot": [-27.06185, 20.128, 7.3193],
							"rotation": [0, 30, 0],
							"uv": {
								"north": {"uv": [1034.24479, 169.27083], "uv_size": [1.69271, 0]},
								"east": {"uv": [988.54167, 223.4375], "uv_size": [8.46354, 0]},
								"south": {"uv": [1078.25521, 155.72917], "uv_size": [1.69271, 0]},
								"west": {"uv": [1186.58854, 179.42708], "uv_size": [8.46354, 0]},
								"up": {"uv": [1098.56771, 187.89062], "uv_size": [1.69271, 8.46354]},
								"down": {"uv": [1073.17708, 274.21875], "uv_size": [1.69271, -8.46354]}
							}
						},
						{
							"origin": [-22.85815, 20.128, 12.55234],
							"size": [2.176, 0.576, 8.576],
							"pivot": [-22.85815, 20.128, 18.95234],
							"rotation": [0, 30, 0],
							"uv": {
								"north": {"uv": [1034.24479, 169.27083], "uv_size": [1.69271, 0]},
								"east": {"uv": [988.54167, 223.4375], "uv_size": [8.46354, 0]},
								"south": {"uv": [1078.25521, 155.72917], "uv_size": [1.69271, 0]},
								"west": {"uv": [1186.58854, 179.42708], "uv_size": [8.46354, 0]},
								"up": {"uv": [1098.56771, 187.89062], "uv_size": [1.69271, 8.46354]},
								"down": {"uv": [1073.17708, 274.21875], "uv_size": [1.69271, -8.46354]}
							}
						},
						{
							"origin": [-22.85815, 20.128, 5.1433],
							"size": [2.176, 0.576, 7.776],
							"pivot": [-22.85815, 20.128, 7.3193],
							"rotation": [0, -30, 0],
							"uv": {
								"north": {"uv": [1034.24479, 169.27083], "uv_size": [1.69271, 0]},
								"east": {"uv": [988.54167, 223.4375], "uv_size": [8.46354, 0]},
								"south": {"uv": [1078.25521, 155.72917], "uv_size": [1.69271, 0]},
								"west": {"uv": [1186.58854, 179.42708], "uv_size": [8.46354, 0]},
								"up": {"uv": [1098.56771, 187.89062], "uv_size": [1.69271, 8.46354]},
								"down": {"uv": [1073.17708, 274.21875], "uv_size": [1.69271, -8.46354]}
							}
						},
						{
							"origin": [-30.67166, 20.128, 11.81015],
							"size": [2.176, 0.576, 8.576],
							"pivot": [-28.49566, 20.128, 18.21015],
							"rotation": [0, -45, 0],
							"uv": {
								"north": {"uv": [1034.24479, 169.27083], "uv_size": [1.69271, 0]},
								"east": {"uv": [988.54167, 223.4375], "uv_size": [8.46354, 0]},
								"south": {"uv": [1078.25521, 155.72917], "uv_size": [1.69271, 0]},
								"west": {"uv": [1186.58854, 179.42708], "uv_size": [8.46354, 0]},
								"up": {"uv": [1098.56771, 187.89062], "uv_size": [1.69271, 8.46354]},
								"down": {"uv": [1073.17708, 274.21875], "uv_size": [1.69271, -8.46354]}
							}
						},
						{
							"origin": [-30.67166, 20.128, 5.88549],
							"size": [2.176, 0.576, 7.776],
							"pivot": [-28.49566, 20.128, 8.06149],
							"rotation": [0, 45, 0],
							"uv": {
								"north": {"uv": [1034.24479, 169.27083], "uv_size": [1.69271, 0]},
								"east": {"uv": [988.54167, 223.4375], "uv_size": [8.46354, 0]},
								"south": {"uv": [1078.25521, 155.72917], "uv_size": [1.69271, 0]},
								"west": {"uv": [1186.58854, 179.42708], "uv_size": [8.46354, 0]},
								"up": {"uv": [1098.56771, 187.89062], "uv_size": [1.69271, 8.46354]},
								"down": {"uv": [1073.17708, 274.21875], "uv_size": [1.69271, -8.46354]}
							}
						},
						{
							"origin": [-21.42434, 20.128, 11.81015],
							"size": [2.176, 0.576, 8.576],
							"pivot": [-21.42434, 20.128, 18.21015],
							"rotation": [0, 45, 0],
							"uv": {
								"north": {"uv": [1034.24479, 169.27083], "uv_size": [1.69271, 0]},
								"east": {"uv": [988.54167, 223.4375], "uv_size": [8.46354, 0]},
								"south": {"uv": [1078.25521, 155.72917], "uv_size": [1.69271, 0]},
								"west": {"uv": [1186.58854, 179.42708], "uv_size": [8.46354, 0]},
								"up": {"uv": [1098.56771, 187.89062], "uv_size": [1.69271, 8.46354]},
								"down": {"uv": [1073.17708, 274.21875], "uv_size": [1.69271, -8.46354]}
							}
						},
						{
							"origin": [-21.42434, 20.128, 5.88549],
							"size": [2.176, 0.576, 7.776],
							"pivot": [-21.42434, 20.128, 8.06149],
							"rotation": [0, -45, 0],
							"uv": {
								"north": {"uv": [1034.24479, 169.27083], "uv_size": [1.69271, 0]},
								"east": {"uv": [988.54167, 223.4375], "uv_size": [8.46354, 0]},
								"south": {"uv": [1078.25521, 155.72917], "uv_size": [1.69271, 0]},
								"west": {"uv": [1186.58854, 179.42708], "uv_size": [8.46354, 0]},
								"up": {"uv": [1098.56771, 187.89062], "uv_size": [1.69271, 8.46354]},
								"down": {"uv": [1073.17708, 274.21875], "uv_size": [1.69271, -8.46354]}
							}
						},
						{
							"origin": [-31.86452, 20.128, 13.12215],
							"size": [2.176, 0.576, 6.176],
							"pivot": [-29.68852, 20.128, 17.12215],
							"rotation": [0, -60, 0],
							"uv": {
								"north": {"uv": [1034.24479, 169.27083], "uv_size": [1.69271, 0]},
								"east": {"uv": [988.54167, 223.4375], "uv_size": [8.46354, 0]},
								"south": {"uv": [1078.25521, 155.72917], "uv_size": [1.69271, 0]},
								"west": {"uv": [1186.58854, 179.42708], "uv_size": [8.46354, 0]},
								"up": {"uv": [1098.56771, 187.89062], "uv_size": [1.69271, 8.46354]},
								"down": {"uv": [1073.17708, 274.21875], "uv_size": [1.69271, -8.46354]}
							}
						},
						{
							"origin": [-31.86452, 20.128, 6.97349],
							"size": [2.176, 0.576, 7.776],
							"pivot": [-29.68852, 20.128, 9.14949],
							"rotation": [0, 60, 0],
							"uv": {
								"north": {"uv": [1034.24479, 169.27083], "uv_size": [1.69271, 0]},
								"east": {"uv": [988.54167, 223.4375], "uv_size": [8.46354, 0]},
								"south": {"uv": [1078.25521, 155.72917], "uv_size": [1.69271, 0]},
								"west": {"uv": [1186.58854, 179.42708], "uv_size": [8.46354, 0]},
								"up": {"uv": [1098.56771, 187.89062], "uv_size": [1.69271, 8.46354]},
								"down": {"uv": [1073.17708, 274.21875], "uv_size": [1.69271, -8.46354]}
							}
						},
						{
							"origin": [-20.23148, 20.128, 13.12215],
							"size": [2.176, 0.576, 6.176],
							"pivot": [-20.23148, 20.128, 17.12215],
							"rotation": [0, 60, 0],
							"uv": {
								"north": {"uv": [1034.24479, 169.27083], "uv_size": [1.69271, 0]},
								"east": {"uv": [988.54167, 223.4375], "uv_size": [8.46354, 0]},
								"south": {"uv": [1078.25521, 155.72917], "uv_size": [1.69271, 0]},
								"west": {"uv": [1186.58854, 179.42708], "uv_size": [8.46354, 0]},
								"up": {"uv": [1098.56771, 187.89062], "uv_size": [1.69271, 8.46354]},
								"down": {"uv": [1073.17708, 274.21875], "uv_size": [1.69271, -8.46354]}
							}
						},
						{
							"origin": [-20.23148, 20.128, 6.97349],
							"size": [2.176, 0.576, 7.776],
							"pivot": [-20.23148, 20.128, 9.14949],
							"rotation": [0, -60, 0],
							"uv": {
								"north": {"uv": [1034.24479, 169.27083], "uv_size": [1.69271, 0]},
								"east": {"uv": [988.54167, 223.4375], "uv_size": [8.46354, 0]},
								"south": {"uv": [1078.25521, 155.72917], "uv_size": [1.69271, 0]},
								"west": {"uv": [1186.58854, 179.42708], "uv_size": [8.46354, 0]},
								"up": {"uv": [1098.56771, 187.89062], "uv_size": [1.69271, 8.46354]},
								"down": {"uv": [1073.17708, 274.21875], "uv_size": [1.69271, -8.46354]}
							}
						},
						{
							"origin": [-32.73514, 20.128, 11.76248],
							"size": [2.176, 0.576, 6.176],
							"pivot": [-30.55914, 20.128, 15.76248],
							"rotation": [0, -75, 0],
							"uv": {
								"north": {"uv": [1034.24479, 169.27083], "uv_size": [1.69271, 0]},
								"east": {"uv": [988.54167, 223.4375], "uv_size": [8.46354, 0]},
								"south": {"uv": [1078.25521, 155.72917], "uv_size": [1.69271, 0]},
								"west": {"uv": [1186.58854, 179.42708], "uv_size": [8.46354, 0]},
								"up": {"uv": [1098.56771, 187.89062], "uv_size": [1.69271, 8.46354]},
								"down": {"uv": [1073.17708, 274.21875], "uv_size": [1.69271, -8.46354]}
							}
						},
						{
							"origin": [-32.73514, 20.128, 8.33316],
							"size": [2.176, 0.576, 7.776],
							"pivot": [-30.55914, 20.128, 10.50916],
							"rotation": [0, 75, 0],
							"uv": {
								"north": {"uv": [1034.24479, 169.27083], "uv_size": [1.69271, 0]},
								"east": {"uv": [988.54167, 223.4375], "uv_size": [8.46354, 0]},
								"south": {"uv": [1078.25521, 155.72917], "uv_size": [1.69271, 0]},
								"west": {"uv": [1186.58854, 179.42708], "uv_size": [8.46354, 0]},
								"up": {"uv": [1098.56771, 187.89062], "uv_size": [1.69271, 8.46354]},
								"down": {"uv": [1073.17708, 274.21875], "uv_size": [1.69271, -8.46354]}
							}
						},
						{
							"origin": [-19.36086, 20.128, 11.76248],
							"size": [2.176, 0.576, 6.176],
							"pivot": [-19.36086, 20.128, 15.76248],
							"rotation": [0, 75, 0],
							"uv": {
								"north": {"uv": [1034.24479, 169.27083], "uv_size": [1.69271, 0]},
								"east": {"uv": [988.54167, 223.4375], "uv_size": [8.46354, 0]},
								"south": {"uv": [1078.25521, 155.72917], "uv_size": [1.69271, 0]},
								"west": {"uv": [1186.58854, 179.42708], "uv_size": [8.46354, 0]},
								"up": {"uv": [1098.56771, 187.89062], "uv_size": [1.69271, 8.46354]},
								"down": {"uv": [1073.17708, 274.21875], "uv_size": [1.69271, -8.46354]}
							}
						},
						{
							"origin": [-19.36086, 20.128, 8.33316],
							"size": [2.176, 0.576, 7.776],
							"pivot": [-19.36086, 20.128, 10.50916],
							"rotation": [0, -75, 0],
							"uv": {
								"north": {"uv": [1034.24479, 169.27083], "uv_size": [1.69271, 0]},
								"east": {"uv": [988.54167, 223.4375], "uv_size": [8.46354, 0]},
								"south": {"uv": [1078.25521, 155.72917], "uv_size": [1.69271, 0]},
								"west": {"uv": [1186.58854, 179.42708], "uv_size": [8.46354, 0]},
								"up": {"uv": [1098.56771, 187.89062], "uv_size": [1.69271, 8.46354]},
								"down": {"uv": [1073.17708, 274.21875], "uv_size": [1.69271, -8.46354]}
							}
						},
						{
							"origin": [-33.22418, 20.128, 14.22382],
							"size": [2.176, 0.576, 2.176],
							"pivot": [-31.04818, 20.128, 14.22382],
							"rotation": [0, -90, 0],
							"uv": {
								"north": {"uv": [1034.24479, 169.27083], "uv_size": [1.69271, 0]},
								"east": {"uv": [988.54167, 223.4375], "uv_size": [8.46354, 0]},
								"south": {"uv": [1078.25521, 155.72917], "uv_size": [1.69271, 0]},
								"west": {"uv": [1186.58854, 179.42708], "uv_size": [8.46354, 0]},
								"up": {"uv": [1098.56771, 187.89062], "uv_size": [1.69271, 8.46354]},
								"down": {"uv": [1073.17708, 274.21875], "uv_size": [1.69271, -8.46354]}
							}
						},
						{
							"origin": [-33.22418, 20.128, 9.87182],
							"size": [2.176, 0.576, 14.976],
							"pivot": [-31.04818, 20.128, 12.04782],
							"rotation": [0, 90, 0],
							"uv": {
								"north": {"uv": [1034.24479, 169.27083], "uv_size": [1.69271, 0]},
								"east": {"uv": [988.54167, 223.4375], "uv_size": [8.46354, 0]},
								"south": {"uv": [1078.25521, 155.72917], "uv_size": [1.69271, 0]},
								"west": {"uv": [1186.58854, 179.42708], "uv_size": [8.46354, 0]},
								"up": {"uv": [1098.56771, 187.89062], "uv_size": [1.69271, 8.46354]},
								"down": {"uv": [1073.17708, 274.21875], "uv_size": [1.69271, -8.46354]}
							}
						},
						{
							"origin": [-18.87182, 20.128, 14.22382],
							"size": [2.176, 0.576, 2.176],
							"pivot": [-18.87182, 20.128, 14.22382],
							"rotation": [0, 90, 0],
							"uv": {
								"north": {"uv": [1034.24479, 169.27083], "uv_size": [1.69271, 0]},
								"east": {"uv": [988.54167, 223.4375], "uv_size": [8.46354, 0]},
								"south": {"uv": [1078.25521, 155.72917], "uv_size": [1.69271, 0]},
								"west": {"uv": [1186.58854, 179.42708], "uv_size": [8.46354, 0]},
								"up": {"uv": [1098.56771, 187.89062], "uv_size": [1.69271, 8.46354]},
								"down": {"uv": [1073.17708, 274.21875], "uv_size": [1.69271, -8.46354]}
							}
						},
						{
							"origin": [-18.87182, 20.128, 9.87182],
							"size": [2.176, 0.576, 2.176],
							"pivot": [-18.87182, 20.128, 12.04782],
							"rotation": [0, -90, 0],
							"uv": {
								"north": {"uv": [1034.24479, 169.27083], "uv_size": [1.69271, 0]},
								"east": {"uv": [988.54167, 223.4375], "uv_size": [8.46354, 0]},
								"south": {"uv": [1078.25521, 155.72917], "uv_size": [1.69271, 0]},
								"west": {"uv": [1186.58854, 179.42708], "uv_size": [8.46354, 0]},
								"up": {"uv": [1098.56771, 187.89062], "uv_size": [1.69271, 8.46354]},
								"down": {"uv": [1073.17708, 274.21875], "uv_size": [1.69271, -8.46354]}
							}
						},
						{
							"origin": [-27.66081, 20.128, 12.89815],
							"size": [2.176, 0.576, 8.576],
							"pivot": [-25.48481, 20.128, 19.29815],
							"rotation": [0, -15, 0],
							"uv": {
								"north": {"uv": [1034.24479, 169.27083], "uv_size": [1.69271, 0]},
								"east": {"uv": [988.54167, 223.4375], "uv_size": [8.46354, 0]},
								"south": {"uv": [1078.25521, 155.72917], "uv_size": [1.69271, 0]},
								"west": {"uv": [1186.58854, 179.42708], "uv_size": [8.46354, 0]},
								"up": {"uv": [1098.56771, 187.89062], "uv_size": [1.69271, 8.46354]},
								"down": {"uv": [1073.17708, 274.21875], "uv_size": [1.69271, -8.46354]}
							}
						},
						{
							"origin": [-27.66081, 20.128, 4.79749],
							"size": [2.176, 0.576, 4.576],
							"pivot": [-25.48481, 20.128, 6.97349],
							"rotation": [0, 15, 0],
							"uv": {
								"north": {"uv": [1034.24479, 169.27083], "uv_size": [1.69271, 0]},
								"east": {"uv": [988.54167, 223.4375], "uv_size": [8.46354, 0]},
								"south": {"uv": [1078.25521, 155.72917], "uv_size": [1.69271, 0]},
								"west": {"uv": [1186.58854, 179.42708], "uv_size": [8.46354, 0]},
								"up": {"uv": [1098.56771, 187.89062], "uv_size": [1.69271, 8.46354]},
								"down": {"uv": [1073.17708, 274.21875], "uv_size": [1.69271, -8.46354]}
							}
						},
						{
							"origin": [-24.43519, 20.128, 12.89815],
							"size": [2.176, 0.576, 8.576],
							"pivot": [-24.43519, 20.128, 19.29815],
							"rotation": [0, 15, 0],
							"uv": {
								"north": {"uv": [1034.24479, 169.27083], "uv_size": [1.69271, 0]},
								"east": {"uv": [988.54167, 223.4375], "uv_size": [8.46354, 0]},
								"south": {"uv": [1078.25521, 155.72917], "uv_size": [1.69271, 0]},
								"west": {"uv": [1186.58854, 179.42708], "uv_size": [8.46354, 0]},
								"up": {"uv": [1098.56771, 187.89062], "uv_size": [1.69271, 8.46354]},
								"down": {"uv": [1073.17708, 274.21875], "uv_size": [1.69271, -8.46354]}
							}
						},
						{
							"origin": [-24.43519, 20.128, 4.79749],
							"size": [2.176, 0.576, 4.576],
							"pivot": [-24.43519, 20.128, 6.97349],
							"rotation": [0, -15, 0],
							"uv": {
								"north": {"uv": [1034.24479, 169.27083], "uv_size": [1.69271, 0]},
								"east": {"uv": [988.54167, 223.4375], "uv_size": [8.46354, 0]},
								"south": {"uv": [1078.25521, 155.72917], "uv_size": [1.69271, 0]},
								"west": {"uv": [1186.58854, 179.42708], "uv_size": [8.46354, 0]},
								"up": {"uv": [1098.56771, 187.89062], "uv_size": [1.69271, 8.46354]},
								"down": {"uv": [1073.17708, 274.21875], "uv_size": [1.69271, -8.46354]}
							}
						}
					]
				},
				{
					"name": "bone3",
					"parent": "Circulos",
					"pivot": [-42.76, 8.416, 34.984],
					"cubes": [
						{
							"origin": [-26.33871, 20.128, 5.40973],
							"size": [2.75743, 0.576, 2.75743],
							"uv": {
								"north": {"uv": [1034.24479, 169.27083], "uv_size": [1.69271, 0]},
								"east": {"uv": [988.54167, 223.4375], "uv_size": [8.46354, 0]},
								"south": {"uv": [1078.25521, 155.72917], "uv_size": [1.69271, 0]},
								"west": {"uv": [1186.58854, 179.42708], "uv_size": [8.46354, 0]},
								"up": {"uv": [1098.56771, 187.89062], "uv_size": [1.69271, 8.46354]},
								"down": {"uv": [1073.17708, 274.21875], "uv_size": [1.69271, -8.46354]}
							}
						},
						{
							"origin": [-26.33871, 20.128, -12.77758],
							"size": [2.75743, 0.576, 2.75743],
							"uv": {
								"north": {"uv": [1034.24479, 169.27083], "uv_size": [1.69271, 0]},
								"east": {"uv": [988.54167, 223.4375], "uv_size": [8.46354, 0]},
								"south": {"uv": [1078.25521, 155.72917], "uv_size": [1.69271, 0]},
								"west": {"uv": [1186.58854, 179.42708], "uv_size": [8.46354, 0]},
								"up": {"uv": [1098.56771, 187.89062], "uv_size": [1.69271, 8.46354]},
								"down": {"uv": [1073.17708, 274.21875], "uv_size": [1.69271, -8.46354]}
							}
						},
						{
							"origin": [-26.33871, 20.128, 5.40973],
							"size": [2.75743, 0.576, 2.75743],
							"uv": {
								"north": {"uv": [1034.24479, 169.27083], "uv_size": [1.69271, 0]},
								"east": {"uv": [988.54167, 223.4375], "uv_size": [8.46354, 0]},
								"south": {"uv": [1078.25521, 155.72917], "uv_size": [1.69271, 0]},
								"west": {"uv": [1186.58854, 179.42708], "uv_size": [8.46354, 0]},
								"up": {"uv": [1098.56771, 187.89062], "uv_size": [1.69271, 8.46354]},
								"down": {"uv": [1073.17708, 274.21875], "uv_size": [1.69271, -8.46354]}
							}
						},
						{
							"origin": [-26.33871, 20.128, -12.77758],
							"size": [2.75743, 0.576, 2.75743],
							"uv": {
								"north": {"uv": [1034.24479, 169.27083], "uv_size": [1.69271, 0]},
								"east": {"uv": [988.54167, 223.4375], "uv_size": [8.46354, 0]},
								"south": {"uv": [1078.25521, 155.72917], "uv_size": [1.69271, 0]},
								"west": {"uv": [1186.58854, 179.42708], "uv_size": [8.46354, 0]},
								"up": {"uv": [1098.56771, 187.89062], "uv_size": [1.69271, 8.46354]},
								"down": {"uv": [1073.17708, 274.21875], "uv_size": [1.69271, -8.46354]}
							}
						},
						{
							"origin": [-30.3809, 20.128, -2.13452],
							"size": [2.75743, 0.576, 9.95743],
							"pivot": [-27.62347, 20.128, 5.06548],
							"rotation": [0, -30, 0],
							"uv": {
								"north": {"uv": [1034.24479, 169.27083], "uv_size": [1.69271, 0]},
								"east": {"uv": [988.54167, 223.4375], "uv_size": [8.46354, 0]},
								"south": {"uv": [1078.25521, 155.72917], "uv_size": [1.69271, 0]},
								"west": {"uv": [1186.58854, 179.42708], "uv_size": [8.46354, 0]},
								"up": {"uv": [1098.56771, 187.89062], "uv_size": [1.69271, 8.46354]},
								"down": {"uv": [1073.17708, 274.21875], "uv_size": [1.69271, -8.46354]}
							}
						},
						{
							"origin": [-30.3809, 20.128, -12.43333],
							"size": [2.75743, 0.576, 9.15743],
							"pivot": [-27.62347, 20.128, -9.67591],
							"rotation": [0, 30, 0],
							"uv": {
								"north": {"uv": [1034.24479, 169.27083], "uv_size": [1.69271, 0]},
								"east": {"uv": [988.54167, 223.4375], "uv_size": [8.46354, 0]},
								"south": {"uv": [1078.25521, 155.72917], "uv_size": [1.69271, 0]},
								"west": {"uv": [1186.58854, 179.42708], "uv_size": [8.46354, 0]},
								"up": {"uv": [1098.56771, 187.89062], "uv_size": [1.69271, 8.46354]},
								"down": {"uv": [1073.17708, 274.21875], "uv_size": [1.69271, -8.46354]}
							}
						},
						{
							"origin": [-22.29653, 20.128, -2.13452],
							"size": [2.75743, 0.576, 9.95743],
							"pivot": [-22.29653, 20.128, 5.06548],
							"rotation": [0, 30, 0],
							"uv": {
								"north": {"uv": [1034.24479, 169.27083], "uv_size": [1.69271, 0]},
								"east": {"uv": [988.54167, 223.4375], "uv_size": [8.46354, 0]},
								"south": {"uv": [1078.25521, 155.72917], "uv_size": [1.69271, 0]},
								"west": {"uv": [1186.58854, 179.42708], "uv_size": [8.46354, 0]},
								"up": {"uv": [1098.56771, 187.89062], "uv_size": [1.69271, 8.46354]},
								"down": {"uv": [1073.17708, 274.21875], "uv_size": [1.69271, -8.46354]}
							}
						},
						{
							"origin": [-22.29653, 20.128, -12.43333],
							"size": [2.75743, 0.576, 9.15743],
							"pivot": [-22.29653, 20.128, -9.67591],
							"rotation": [0, -30, 0],
							"uv": {
								"north": {"uv": [1034.24479, 169.27083], "uv_size": [1.69271, 0]},
								"east": {"uv": [988.54167, 223.4375], "uv_size": [8.46354, 0]},
								"south": {"uv": [1078.25521, 155.72917], "uv_size": [1.69271, 0]},
								"west": {"uv": [1186.58854, 179.42708], "uv_size": [8.46354, 0]},
								"up": {"uv": [1098.56771, 187.89062], "uv_size": [1.69271, 8.46354]},
								"down": {"uv": [1073.17708, 274.21875], "uv_size": [1.69271, -8.46354]}
							}
						},
						{
							"origin": [-32.19782, 20.128, -3.07503],
							"size": [2.75743, 0.576, 9.95743],
							"pivot": [-29.44039, 20.128, 4.12497],
							"rotation": [0, -45, 0],
							"uv": {
								"north": {"uv": [1034.24479, 169.27083], "uv_size": [1.69271, 0]},
								"east": {"uv": [988.54167, 223.4375], "uv_size": [8.46354, 0]},
								"south": {"uv": [1078.25521, 155.72917], "uv_size": [1.69271, 0]},
								"west": {"uv": [1186.58854, 179.42708], "uv_size": [8.46354, 0]},
								"up": {"uv": [1098.56771, 187.89062], "uv_size": [1.69271, 8.46354]},
								"down": {"uv": [1073.17708, 274.21875], "uv_size": [1.69271, -8.46354]}
							}
						},
						{
							"origin": [-32.19782, 20.128, -11.49283],
							"size": [2.75743, 0.576, 9.15743],
							"pivot": [-29.44039, 20.128, -8.7354],
							"rotation": [0, 45, 0],
							"uv": {
								"north": {"uv": [1034.24479, 169.27083], "uv_size": [1.69271, 0]},
								"east": {"uv": [988.54167, 223.4375], "uv_size": [8.46354, 0]},
								"south": {"uv": [1078.25521, 155.72917], "uv_size": [1.69271, 0]},
								"west": {"uv": [1186.58854, 179.42708], "uv_size": [8.46354, 0]},
								"up": {"uv": [1098.56771, 187.89062], "uv_size": [1.69271, 8.46354]},
								"down": {"uv": [1073.17708, 274.21875], "uv_size": [1.69271, -8.46354]}
							}
						},
						{
							"origin": [-20.47961, 20.128, -3.07503],
							"size": [2.75743, 0.576, 9.95743],
							"pivot": [-20.47961, 20.128, 4.12497],
							"rotation": [0, 45, 0],
							"uv": {
								"north": {"uv": [1034.24479, 169.27083], "uv_size": [1.69271, 0]},
								"east": {"uv": [988.54167, 223.4375], "uv_size": [8.46354, 0]},
								"south": {"uv": [1078.25521, 155.72917], "uv_size": [1.69271, 0]},
								"west": {"uv": [1186.58854, 179.42708], "uv_size": [8.46354, 0]},
								"up": {"uv": [1098.56771, 187.89062], "uv_size": [1.69271, 8.46354]},
								"down": {"uv": [1073.17708, 274.21875], "uv_size": [1.69271, -8.46354]}
							}
						},
						{
							"origin": [-20.47961, 20.128, -11.49283],
							"size": [2.75743, 0.576, 9.15743],
							"pivot": [-20.47961, 20.128, -8.7354],
							"rotation": [0, -45, 0],
							"uv": {
								"north": {"uv": [1034.24479, 169.27083], "uv_size": [1.69271, 0]},
								"east": {"uv": [988.54167, 223.4375], "uv_size": [8.46354, 0]},
								"south": {"uv": [1078.25521, 155.72917], "uv_size": [1.69271, 0]},
								"west": {"uv": [1186.58854, 179.42708], "uv_size": [8.46354, 0]},
								"up": {"uv": [1098.56771, 187.89062], "uv_size": [1.69271, 8.46354]},
								"down": {"uv": [1073.17708, 274.21875], "uv_size": [1.69271, -8.46354]}
							}
						},
						{
							"origin": [-33.70941, 20.128, -4.45374],
							"size": [2.75743, 0.576, 9.95743],
							"pivot": [-30.95198, 20.128, 2.74626],
							"rotation": [0, -60, 0],
							"uv": {
								"north": {"uv": [1034.24479, 169.27083], "uv_size": [1.69271, 0]},
								"east": {"uv": [988.54167, 223.4375], "uv_size": [8.46354, 0]},
								"south": {"uv": [1078.25521, 155.72917], "uv_size": [1.69271, 0]},
								"west": {"uv": [1186.58854, 179.42708], "uv_size": [8.46354, 0]},
								"up": {"uv": [1098.56771, 187.89062], "uv_size": [1.69271, 8.46354]},
								"down": {"uv": [1073.17708, 274.21875], "uv_size": [1.69271, -8.46354]}
							}
						},
						{
							"origin": [-33.70941, 20.128, -10.11411],
							"size": [2.75743, 0.576, 9.15743],
							"pivot": [-30.95198, 20.128, -7.35669],
							"rotation": [0, 60, 0],
							"uv": {
								"north": {"uv": [1034.24479, 169.27083], "uv_size": [1.69271, 0]},
								"east": {"uv": [988.54167, 223.4375], "uv_size": [8.46354, 0]},
								"south": {"uv": [1078.25521, 155.72917], "uv_size": [1.69271, 0]},
								"west": {"uv": [1186.58854, 179.42708], "uv_size": [8.46354, 0]},
								"up": {"uv": [1098.56771, 187.89062], "uv_size": [1.69271, 8.46354]},
								"down": {"uv": [1073.17708, 274.21875], "uv_size": [1.69271, -8.46354]}
							}
						},
						{
							"origin": [-18.96802, 20.128, -4.45374],
							"size": [2.75743, 0.576, 9.95743],
							"pivot": [-18.96802, 20.128, 2.74626],
							"rotation": [0, 60, 0],
							"uv": {
								"north": {"uv": [1034.24479, 169.27083], "uv_size": [1.69271, 0]},
								"east": {"uv": [988.54167, 223.4375], "uv_size": [8.46354, 0]},
								"south": {"uv": [1078.25521, 155.72917], "uv_size": [1.69271, 0]},
								"west": {"uv": [1186.58854, 179.42708], "uv_size": [8.46354, 0]},
								"up": {"uv": [1098.56771, 187.89062], "uv_size": [1.69271, 8.46354]},
								"down": {"uv": [1073.17708, 274.21875], "uv_size": [1.69271, -8.46354]}
							}
						},
						{
							"origin": [-18.96802, 20.128, -10.11411],
							"size": [2.75743, 0.576, 9.15743],
							"pivot": [-18.96802, 20.128, -7.35669],
							"rotation": [0, -60, 0],
							"uv": {
								"north": {"uv": [1034.24479, 169.27083], "uv_size": [1.69271, 0]},
								"east": {"uv": [988.54167, 223.4375], "uv_size": [8.46354, 0]},
								"south": {"uv": [1078.25521, 155.72917], "uv_size": [1.69271, 0]},
								"west": {"uv": [1186.58854, 179.42708], "uv_size": [8.46354, 0]},
								"up": {"uv": [1098.56771, 187.89062], "uv_size": [1.69271, 8.46354]},
								"down": {"uv": [1073.17708, 274.21875], "uv_size": [1.69271, -8.46354]}
							}
						},
						{
							"origin": [-34.81265, 20.128, -11.77671],
							"size": [2.75743, 0.576, 15.55743],
							"pivot": [-32.05522, 20.128, 1.02329],
							"rotation": [0, -75, 0],
							"uv": {
								"north": {"uv": [1034.24479, 169.27083], "uv_size": [1.69271, 0]},
								"east": {"uv": [988.54167, 223.4375], "uv_size": [8.46354, 0]},
								"south": {"uv": [1078.25521, 155.72917], "uv_size": [1.69271, 0]},
								"west": {"uv": [1186.58854, 179.42708], "uv_size": [8.46354, 0]},
								"up": {"uv": [1098.56771, 187.89062], "uv_size": [1.69271, 8.46354]},
								"down": {"uv": [1073.17708, 274.21875], "uv_size": [1.69271, -8.46354]}
							}
						},
						{
							"origin": [-34.81265, 20.128, -8.39115],
							"size": [2.75743, 0.576, 9.15743],
							"pivot": [-32.05522, 20.128, -5.63372],
							"rotation": [0, 75, 0],
							"uv": {
								"north": {"uv": [1034.24479, 169.27083], "uv_size": [1.69271, 0]},
								"east": {"uv": [988.54167, 223.4375], "uv_size": [8.46354, 0]},
								"south": {"uv": [1078.25521, 155.72917], "uv_size": [1.69271, 0]},
								"west": {"uv": [1186.58854, 179.42708], "uv_size": [8.46354, 0]},
								"up": {"uv": [1098.56771, 187.89062], "uv_size": [1.69271, 8.46354]},
								"down": {"uv": [1073.17708, 274.21875], "uv_size": [1.69271, -8.46354]}
							}
						},
						{
							"origin": [-17.86478, 20.128, -11.77671],
							"size": [2.75743, 0.576, 15.55743],
							"pivot": [-17.86478, 20.128, 1.02329],
							"rotation": [0, 75, 0],
							"uv": {
								"north": {"uv": [1034.24479, 169.27083], "uv_size": [1.69271, 0]},
								"east": {"uv": [988.54167, 223.4375], "uv_size": [8.46354, 0]},
								"south": {"uv": [1078.25521, 155.72917], "uv_size": [1.69271, 0]},
								"west": {"uv": [1186.58854, 179.42708], "uv_size": [8.46354, 0]},
								"up": {"uv": [1098.56771, 187.89062], "uv_size": [1.69271, 8.46354]},
								"down": {"uv": [1073.17708, 274.21875], "uv_size": [1.69271, -8.46354]}
							}
						},
						{
							"origin": [-17.86478, 20.128, -8.39115],
							"size": [2.75743, 0.576, 9.15743],
							"pivot": [-17.86478, 20.128, -5.63372],
							"rotation": [0, -75, 0],
							"uv": {
								"north": {"uv": [1034.24479, 169.27083], "uv_size": [1.69271, 0]},
								"east": {"uv": [988.54167, 223.4375], "uv_size": [8.46354, 0]},
								"south": {"uv": [1078.25521, 155.72917], "uv_size": [1.69271, 0]},
								"west": {"uv": [1186.58854, 179.42708], "uv_size": [8.46354, 0]},
								"up": {"uv": [1098.56771, 187.89062], "uv_size": [1.69271, 8.46354]},
								"down": {"uv": [1073.17708, 274.21875], "uv_size": [1.69271, -8.46354]}
							}
						},
						{
							"origin": [-35.43237, 20.128, -13.7265],
							"size": [2.75743, 0.576, 15.55743],
							"pivot": [-32.67494, 20.128, -0.9265],
							"rotation": [0, -90, 0],
							"uv": {
								"north": {"uv": [1034.24479, 169.27083], "uv_size": [1.69271, 0]},
								"east": {"uv": [988.54167, 223.4375], "uv_size": [8.46354, 0]},
								"south": {"uv": [1078.25521, 155.72917], "uv_size": [1.69271, 0]},
								"west": {"uv": [1186.58854, 179.42708], "uv_size": [8.46354, 0]},
								"up": {"uv": [1098.56771, 187.89062], "uv_size": [1.69271, 8.46354]},
								"down": {"uv": [1073.17708, 274.21875], "uv_size": [1.69271, -8.46354]}
							}
						},
						{
							"origin": [-35.43237, 20.128, -6.44136],
							"size": [2.75743, 0.576, 2.75743],
							"pivot": [-32.67494, 20.128, -3.68393],
							"rotation": [0, 90, 0],
							"uv": {
								"north": {"uv": [1034.24479, 169.27083], "uv_size": [1.69271, 0]},
								"east": {"uv": [988.54167, 223.4375], "uv_size": [8.46354, 0]},
								"south": {"uv": [1078.25521, 155.72917], "uv_size": [1.69271, 0]},
								"west": {"uv": [1186.58854, 179.42708], "uv_size": [8.46354, 0]},
								"up": {"uv": [1098.56771, 187.89062], "uv_size": [1.69271, 8.46354]},
								"down": {"uv": [1073.17708, 274.21875], "uv_size": [1.69271, -8.46354]}
							}
						},
						{
							"origin": [-17.24506, 20.128, -13.7265],
							"size": [2.75743, 0.576, 15.55743],
							"pivot": [-17.24506, 20.128, -0.9265],
							"rotation": [0, 90, 0],
							"uv": {
								"north": {"uv": [1034.24479, 169.27083], "uv_size": [1.69271, 0]},
								"east": {"uv": [988.54167, 223.4375], "uv_size": [8.46354, 0]},
								"south": {"uv": [1078.25521, 155.72917], "uv_size": [1.69271, 0]},
								"west": {"uv": [1186.58854, 179.42708], "uv_size": [8.46354, 0]},
								"up": {"uv": [1098.56771, 187.89062], "uv_size": [1.69271, 8.46354]},
								"down": {"uv": [1073.17708, 274.21875], "uv_size": [1.69271, -8.46354]}
							}
						},
						{
							"origin": [-17.24506, 20.128, -6.44136],
							"size": [2.75743, 0.576, 2.75743],
							"pivot": [-17.24506, 20.128, -3.68393],
							"rotation": [0, -90, 0],
							"uv": {
								"north": {"uv": [1034.24479, 169.27083], "uv_size": [1.69271, 0]},
								"east": {"uv": [988.54167, 223.4375], "uv_size": [8.46354, 0]},
								"south": {"uv": [1078.25521, 155.72917], "uv_size": [1.69271, 0]},
								"west": {"uv": [1186.58854, 179.42708], "uv_size": [8.46354, 0]},
								"up": {"uv": [1098.56771, 187.89062], "uv_size": [1.69271, 8.46354]},
								"down": {"uv": [1073.17708, 274.21875], "uv_size": [1.69271, -8.46354]}
							}
						},
						{
							"origin": [-28.38247, 20.128, -1.69631],
							"size": [2.75743, 0.576, 9.95743],
							"pivot": [-25.62504, 20.128, 5.50369],
							"rotation": [0, -15, 0],
							"uv": {
								"north": {"uv": [1034.24479, 169.27083], "uv_size": [1.69271, 0]},
								"east": {"uv": [988.54167, 223.4375], "uv_size": [8.46354, 0]},
								"south": {"uv": [1078.25521, 155.72917], "uv_size": [1.69271, 0]},
								"west": {"uv": [1186.58854, 179.42708], "uv_size": [8.46354, 0]},
								"up": {"uv": [1098.56771, 187.89062], "uv_size": [1.69271, 8.46354]},
								"down": {"uv": [1073.17708, 274.21875], "uv_size": [1.69271, -8.46354]}
							}
						},
						{
							"origin": [-28.38247, 20.128, -12.87154],
							"size": [2.75743, 0.576, 9.15743],
							"pivot": [-25.62504, 20.128, -10.11411],
							"rotation": [0, 15, 0],
							"uv": {
								"north": {"uv": [1034.24479, 169.27083], "uv_size": [1.69271, 0]},
								"east": {"uv": [988.54167, 223.4375], "uv_size": [8.46354, 0]},
								"south": {"uv": [1078.25521, 155.72917], "uv_size": [1.69271, 0]},
								"west": {"uv": [1186.58854, 179.42708], "uv_size": [8.46354, 0]},
								"up": {"uv": [1098.56771, 187.89062], "uv_size": [1.69271, 8.46354]},
								"down": {"uv": [1073.17708, 274.21875], "uv_size": [1.69271, -8.46354]}
							}
						},
						{
							"origin": [-24.29496, 20.128, -1.69631],
							"size": [2.75743, 0.576, 9.95743],
							"pivot": [-24.29496, 20.128, 5.50369],
							"rotation": [0, 15, 0],
							"uv": {
								"north": {"uv": [1034.24479, 169.27083], "uv_size": [1.69271, 0]},
								"east": {"uv": [988.54167, 223.4375], "uv_size": [8.46354, 0]},
								"south": {"uv": [1078.25521, 155.72917], "uv_size": [1.69271, 0]},
								"west": {"uv": [1186.58854, 179.42708], "uv_size": [8.46354, 0]},
								"up": {"uv": [1098.56771, 187.89062], "uv_size": [1.69271, 8.46354]},
								"down": {"uv": [1073.17708, 274.21875], "uv_size": [1.69271, -8.46354]}
							}
						},
						{
							"origin": [-24.29496, 20.128, -12.87154],
							"size": [2.75743, 0.576, 9.15743],
							"pivot": [-24.29496, 20.128, -10.11411],
							"rotation": [0, -15, 0],
							"uv": {
								"north": {"uv": [1034.24479, 169.27083], "uv_size": [1.69271, 0]},
								"east": {"uv": [988.54167, 223.4375], "uv_size": [8.46354, 0]},
								"south": {"uv": [1078.25521, 155.72917], "uv_size": [1.69271, 0]},
								"west": {"uv": [1186.58854, 179.42708], "uv_size": [8.46354, 0]},
								"up": {"uv": [1098.56771, 187.89062], "uv_size": [1.69271, 8.46354]},
								"down": {"uv": [1073.17708, 274.21875], "uv_size": [1.69271, -8.46354]}
							}
						}
					]
				}
			]
		}
	]
}